{
  "users": [
    {
      "firstName": "Homer",
      "lastName": "Simpson",
      "email": "homer@simpson.com",
      "password": "secret",
      "_id": "0dbe3738-4175-4b83-aa81-3dc5ce9d931b"
    },
    {
      "firstName": "Marge",
      "lastName": "Simpson",
      "email": "marge@simpson.com",
      "password": "secret",
      "_id": "20c84954-70bc-4479-bec7-4dbd74c06db9"
    },
    {
      "firstName": "Bart",
      "lastName": "Simpson",
      "email": "bart@simpson.com",
      "password": "secret",
      "_id": "7cccf9b7-6c38-41fa-8a75-b2bf40d31118"
    }
  ]
}